asciicodex/__init__.py
asciicodex/codex.py
asciicodex-0.0.5.dist-info/LICENSE
asciicodex-0.0.5.dist-info/METADATA
asciicodex-0.0.5.dist-info/WHEEL
asciicodex-0.0.5.dist-info/top_level.txt
asciicodex-0.0.5.dist-info/RECORD
