Metadata-Version: 2.1
Name: asciicodex
Version: 0.0.5
Summary: A simple class to encode given string using uncode
Home-page: https://github.com/MineisZarox/Codex
Author: MineisZarox
Author-email: mineiszarox@gmail.com
Project-URL: Bug Tracker, https://github.com/MineisZarox/Codex/issues
Classifier: Programming Language :: Python :: 3
Classifier: License :: OSI Approved :: MIT License
Classifier: Operating System :: OS Independent
Requires-Python: >=3.7
License-File: LICENSE
